Workbook

Sheet Dashboard
A1: Yinglima ERP — System Testing & Quality Dashboard
A2: Live Test Execution Summary & Real-time Progress Tracking
B4: Total Test Cases | C4: =COUNTA('Master Checklist'!C4:C120) -> 111 | D4: Passed | E4: =COUNTIF('Master Checklist'!G4:G120, "PASS") -> 0 | F4: Failed | G4: =COUNTIF('Master Checklist'!G4:G120, "FAIL") -> 0 | H4: Pending | I4: =COUNTIF('Master Checklist'!G4:G120, "PENDING") -> 111
A7: # | B7: Module Name | C7: Target Route | D7: Total Tests | E7: Passed | F7: Failed | G7: Pending | H7: Pass Rate (%)
A8: 1 | B8: Suppliers Module | C8: /suppliers | D8: =COUNTIF('Master Checklist'!C4:C120, "SUP-*") -> 12 | E8: =COUNTIFS('Master Checklist'!C4:C120, "SUP-*", 'Master Checklist'!G4:G120, "PASS") -> 0 | F8: =COUNTIFS('Master Checklist'!C4:C120, "SUP-*", 'Master Checklist'!G4:G120, "FAIL") -> 0 | G8: =COUNTIFS('Master Checklist'!C4:C120, "SUP-*", 'Master Checklist'!G4:G120, "PENDING") -> 12 | H8: =IF(D8>0, ROUND((E8/D8)*100, 1), 0) -> 0
A9: 2 | B9: Buyers Module | C9: /buyers | D9: =COUNTIF('Master Checklist'!C4:C120, "BUY-*") -> 8 | E9: =COUNTIFS('Master Checklist'!C4:C120, "BUY-*", 'Master Checklist'!G4:G120, "PASS") -> 0 | F9: =COUNTIFS('Master Checklist'!C4:C120, "BUY-*", 'Master Checklist'!G4:G120, "FAIL") -> 0 | G9: =COUNTIFS('Master Checklist'!C4:C120, "BUY-*", 'Master Checklist'!G4:G120, "PENDING") -> 8 | H9: =IF(D9>0, ROUND((E9/D9)*100, 1), 0) -> 0
A10: 3 | B10: Product Master Module | C10: /products | D10: =COUNTIF('Master Checklist'!C4:C120, "PRD-*") -> 15 | E10: =COUNTIFS('Master Checklist'!C4:C120, "PRD-*", 'Master Checklist'!G4:G120, "PASS") -> 0 | F10: =COUNTIFS('Master Checklist'!C4:C120, "PRD-*", 'Master Checklist'!G4:G120, "FAIL") -> 0 | G10: =COUNTIFS('Master Checklist'!C4:C120, "PRD-*", 'Master Checklist'!G4:G120, "PENDING") -> 15 | H10: =IF(D10>0, ROUND((E10/D10)*100, 1), 0) -> 0
A11: 4 | B11: Product Prices Module | C11: /product-prices | D11: =COUNTIF('Master Checklist'!C4:C120, "PRC-*") -> 10 | E11: =COUNTIFS('Master Checklist'!C4:C120, "PRC-*", 'Master Checklist'!G4:G120, "PASS") -> 0 | F11: =COUNTIFS('Master Checklist'!C4:C120, "PRC-*", 'Master Checklist'!G4:G120, "FAIL") -> 0 | G11: =COUNTIFS('Master Checklist'!C4:C120, "PRC-*", 'Master Checklist'!G4:G120, "PENDING") -> 10 | H11: =IF(D11>0, ROUND((E11/D11)*100, 1), 0) -> 0
A12: 5 | B12: Inquiries & RFQ Module | C12: /inquiries | D12: =COUNTIF('Master Checklist'!C4:C120, "INQ-*") -> 10 | E12: =COUNTIFS('Master Checklist'!C4:C120, "INQ-*", 'Master Checklist'!G4:G120, "PASS") -> 0 | F12: =COUNTIFS('Master Checklist'!C4:C120, "INQ-*", 'Master Checklist'!G4:G120, "FAIL") -> 0 | G12: =COUNTIFS('Master Checklist'!C4:C120, "INQ-*", 'Master Checklist'!G4:G120, "PENDING") -> 10 | H12: =IF(D12>0, ROUND((E12/D12)*100, 1), 0) -> 0
A13: 6 | B13: Local Purchase Module | C13: /purchase/local | D13: =COUNTIF('Master Checklist'!C4:C120, "LP-*") -> 16 | E13: =COUNTIFS('Master Checklist'!C4:C120, "LP-*", 'Master Checklist'!G4:G120, "PASS") -> 0 | F13: =COUNTIFS('Master Checklist'!C4:C120, "LP-*", 'Master Checklist'!G4:G120, "FAIL") -> 0 | G13: =COUNTIFS('Master Checklist'!C4:C120, "LP-*", 'Master Checklist'!G4:G120, "PENDING") -> 16 | H13: =IF(D13>0, ROUND((E13/D13)*100, 1), 0) -> 0
A14: 7 | B14: Shipment Planning Module | C14: /planning | D14: =COUNTIF('Master Checklist'!C4:C120, "PLN-*") -> 12 | E14: =COUNTIFS('Master Checklist'!C4:C120, "PLN-*", 'Master Checklist'!G4:G120, "PASS") -> 0 | F14: =COUNTIFS('Master Checklist'!C4:C120, "PLN-*", 'Master Checklist'!G4:G120, "FAIL") -> 0 | G14: =COUNTIFS('Master Checklist'!C4:C120, "PLN-*", 'Master Checklist'!G4:G120, "PENDING") -> 12 | H14: =IF(D14>0, ROUND((E14/D14)*100, 1), 0) -> 0
A15: 8 | B15: Sale Process & CI Module | C15: /sale/process | D15: =COUNTIF('Master Checklist'!C4:C120, "SAL-*") -> 20 | E15: =COUNTIFS('Master Checklist'!C4:C120, "SAL-*", 'Master Checklist'!G4:G120, "PASS") -> 0 | F15: =COUNTIFS('Master Checklist'!C4:C120, "SAL-*", 'Master Checklist'!G4:G120, "FAIL") -> 0 | G15: =COUNTIFS('Master Checklist'!C4:C120, "SAL-*", 'Master Checklist'!G4:G120, "PENDING") -> 20 | H15: =IF(D15>0, ROUND((E15/D15)*100, 1), 0) -> 0
A16: 9 | B16: Master Data & Settings | C16: /masters/* | D16: =COUNTIF('Master Checklist'!C4:C120, "MST-*") -> 6 | E16: =COUNTIFS('Master Checklist'!C4:C120, "MST-*", 'Master Checklist'!G4:G120, "PASS") -> 0 | F16: =COUNTIFS('Master Checklist'!C4:C120, "MST-*", 'Master Checklist'!G4:G120, "FAIL") -> 0 | G16: =COUNTIFS('Master Checklist'!C4:C120, "MST-*", 'Master Checklist'!G4:G120, "PENDING") -> 6 | H16: =IF(D16>0, ROUND((E16/D16)*100, 1), 0) -> 0
A17: 10 | B17: User Management & Auth | C17: /users | D17: =COUNTIF('Master Checklist'!C4:C120, "USR-*") -> 2 | E17: =COUNTIFS('Master Checklist'!C4:C120, "USR-*", 'Master Checklist'!G4:G120, "PASS") -> 0 | F17: =COUNTIFS('Master Checklist'!C4:C120, "USR-*", 'Master Checklist'!G4:G120, "FAIL") -> 0 | G17: =COUNTIFS('Master Checklist'!C4:C120, "USR-*", 'Master Checklist'!G4:G120, "PENDING") -> 2 | H17: =IF(D17>0, ROUND((E17/D17)*100, 1), 0) -> 0

Sheet Master Checklist
A1: Yinglima ERP — Complete Manual & Automated Test Checklist
A2: Select PASS / FAIL / BLOCKED in the Status column. Add testing feedback in Notes.
A3: # | B3: Module | C3: Test ID | D3: Test Description | E3: Test Steps | F3: Expected Behavior | G3: Status | H3: Observed Behavior / Notes | I3: Tested By | J3: Date Tested | K3: result
A4: 1 | B4: Suppliers | C4: SUP-01 | D4: Add New Supplier (Happy Path) | E4: 1. Click '+ Add Supplier' 2. Fill Company Name, China, Zhejiang, Wenzhou. 3. Fill Contact Person & Phone. 4. Click Save. | F4: Supplier created; appears at top of table with green success toast. | G4: PENDING | H4: yes | I4: Admin | K4: yes
A5: 2 | B5: Suppliers | C5: SUP-02 | D5: Duplicate Company Name Validation | E5: 1. Click '+ Add Supplier' 2. Type the exact same Company Name as an existing supplier. 3. Blur field. | F5: Red inline warning appears: '⛔ Supplier already exists'. Save button disabled. | G5: PENDING | H5: yes | I5: Admin
A6: 3 | B6: Suppliers | C6: SUP-03 | D6: Similar Supplier Suggestion Dropdown | E6: 1. Type partial name of existing supplier (e.g. 'Dingye'). | F6: Dropdown shows 'EXISTING SIMILAR SUPPLIERS' with matching supplier types. | G6: PENDING | H6: yes | I6: Admin
A7: 4 | B7: Suppliers | C7: SUP-04 | D7: Geographic Cascading Selection | E7: 1. Select Country = 'China'. 2. Select State = 'Zhejiang'. 3. Check City dropdown. | F7: State dropdown lists Chinese provinces. City dropdown filters to Zhejiang cities (Wenzhou, Ningbo). | G7: PENDING | H7: yes | I7: Admin
A8: 5 | B8: Suppliers | C8: SUP-05 | D8: Visit Photo Upload | E8: 1. Upload 2 JPG/PNG photos in Visit Photos area. 2. Save supplier. 3. Open detail modal. | F8: Photos render as thumbnails; clicking opens high-res image modal. | G8: PENDING | H8: yes | I8: Admin
A9: 6 | B9: Suppliers | C9: SUP-06 | D9: Visit Photo Deletion | E9: 1. Edit supplier with photos. 2. Click delete on one photo. 3. Save supplier. | F9: Deleted photo disappears; remaining photo is preserved in database. | G9: PENDING | H9: yes | I9: Admin
A10: 7 | B10: Suppliers | C10: SUP-07 | D10: Video Links Pill Rendering | E10: 1. Add YouTube and Google Drive links in Video Links field. 2. Save and view detail. | F10: Renders interactive pills: '▶️ YouTube' and '📁 Google Drive'. Clicking opens in new tab. | G10: PENDING | H10: yes | I10: Admin
A11: 8 | B11: Suppliers | C11: SUP-08 | D11: Status Governance (New -> Existing) | E11: 1. Change status from 'New' to 'Existing'. 2. Save supplier. 3. Edit supplier again. | F11: Once saved as 'Existing', business rules lock it from reverting back to 'New'. | G11: PENDING | I11: Admin
A12: 9 | B12: Suppliers | C12: SUP-09 | D12: Supplier Search & Filters | E12: 1. Type city name or contact in search box. 2. Filter by Grade 'A'. | F12: Table filters in real-time matching search query and selected grade. | G12: PENDING | I12: Admin
A13: 10 | B13: Suppliers | C13: SUP-10 | D13: Export Suppliers to Excel | E13: 1. Click 'Export' button in top bar. | F13: Downloads formatted Excel file with all active suppliers and complete fields. | G13: PENDING | H13: yes | I13: Admin
A14: 11 | B14: Suppliers | C14: SUP-11 | D14: Soft Delete Supplier | E14: 1. Click delete button on row. 2. Confirm dialog. | F14: Row disappears from active table; 'deleted_at' timestamp set in DB. | G14: PENDING | I14: Admin
A15: 12 | B15: Suppliers | C15: SUP-12 | D15: Duplicate Phone/WeChat Alert | E15: 1. Add supplier with identical phone number to existing supplier. | F15: Warning banner alerts operator of duplicate contact phone number conflict. | G15: PENDING | H15: fail | I15: Admin
A16: 13 | B16: Buyers | C16: BUY-01 | D16: Add New Buyer (Happy Path) | E16: 1. Click '+ Add Buyer'. 2. Enter Inhyma Industrial, India, Mumbai. 3. Enter GST/Tax ID & Contact. 4. Click Save. | F16: Buyer created and visible in list; searchable by name or country. | G16: PENDING | I16: Admin
A17: 14 | B17: Buyers | C17: BUY-02 | D17: Duplicate Buyer Name Check | E17: 1. Try adding buyer with identical existing name. | F17: Red error alert prevents creating duplicate buyer profile. | G17: PENDING | I17: Admin
A18: 15 | B18: Buyers | C18: BUY-03 | D18: Add Delivery Branches | E18: 1. In Buyer form, add 2 delivery branches (e.g. 'Mumbai Central' & 'Nhava Sheva'). 2. Save. | F18: Branches saved in branches array; available in Sale Process destination dropdown. | G18: PENDING | I18: Admin
A19: 16 | B19: Buyers | C19: BUY-04 | D19: Edit Buyer Details | E19: 1. Edit address and phone of an existing buyer. 2. Save and reopen. | F19: Updated address and contact details persist cleanly. | G19: PENDING | I19: Admin
A20: 17 | B20: Buyers | C20: BUY-05 | D20: Soft Delete Buyer | E20: 1. Delete a test buyer. | F20: Buyer disappears from list; cannot be assigned to new Inquiries. | G20: PENDING | I20: Admin
A21: 18 | B21: Buyers | C21: BUY-06 | D21: Export Buyers to Excel | E21: 1. Click 'Export' button. | F21: Generates formatted Excel file with all buyers and branch locations. | G21: PENDING | I21: Admin
A22: 19 | B22: Buyers | C22: BUY-07 | D22: Inquiry Dropdown Linkage | E22: 1. Navigate to '/inquiries/new'. 2. Open Buyer dropdown. | F22: Newly created buyer appears immediately in the dropdown list. | G22: PENDING | I22: Admin
A23: 20 | B23: Buyers | C23: BUY-08 | D23: Sale Process Buyer Linkage | E23: 1. Navigate to '/sale/process/new'. 2. Select Buyer. | F23: Buyer address and branch options populate automatically. | G23: PENDING | I23: Admin
A24: 21 | B24: Product Master | C24: PRD-01 | D24: Add New Product (Happy Path) | E24: 1. Click '+ Add Product'. 2. Enter Name, SKU, Category, UOM. 3. Pick HS Code 8422.30.00. 4. Enter L 88, W 42, H 38. 5. Save. | F24: Product created with auto-calculated CBM 0.140448 m³ and Refund VAT 13.00%. | G24: PENDING | I24: Admin
A25: 22 | B25: Product Master | C25: PRD-02 | D25: Live Dimension to CBM Auto-Math | E25: 1. In product form, type L=100, W=50, H=40. 2. Observe CBM field. | F25: CBM auto-updates to 0.200000 m³ immediately without manual calculation. | G25: PENDING | I25: Admin
A26: 23 | B26: Product Master | C26: PRD-03 | D26: Duplicate Product Name Check | E26: 1. Type an existing product name into Name field. 2. Pause 300ms. | F26: Red inline warning: '⚠️ Product name already exists in master!'. Save disabled. | G26: PENDING | I26: Admin
A27: 24 | B27: Product Master | C27: PRD-04 | D27: HSN Refund VAT Auto-Sync | E27: 1. Select HSN '8422.30.00'. | F27: Refund VAT % auto-populates to 13.00% directly from HSN master table. | G27: PENDING | I27: Admin
... A114: 111 | B114: User Management | C114: USR-02 | D114: Role Permission Enforcement | E114: 1. Log in as Viewer role. 2. Attempt to delete a product or order. | F114: Delete actions are hidden or return 403 Forbidden. | G114: PENDING | I114: Admin
