Workbook

Sheet CI
A1: YINGLIMA IMPORT&EXPORT (WENZHOU) CO., LTD. Email：sales.yinglima@gmail.com Mobile：15068270160,Wechat:+91 8108294930 Address:Room 602, Sixth floor, Jinyu Business Building, Wenzhou Avenue, Nanhui Street, Lucheng District, Wenzhou City, Zhejiang Province
A2: COMMERCIAL INVOICE
A3: Commercial Invoice No | B3: YL-EXP2026-54 | F3: Date | G3: 46198
A4: Shipper's Information | E4: Recipient's Information
A5: Company Name | B5: YINGLIMA IMPORT&EXPORT (WENZHOU) CO., LTD. | E5: Company Name | F5: INHYMA SOLUTIONS LLP
A6: Address | B6: Room 602, Sixth floor, Jinyu Business Building, Wenzhou Avenue, Nanhui Street, Lucheng District, Wenzhou City, Zhejiang Province | E6: Address | F6: Ground Floor, Godown No:2,3,4, Prerna Complex, A-9,Mankoli Road, House Number :1692/A- 9/3, VAL.Bhiwandi, Thane, Maharashtra, 421302,INDIA. GSTIN/UIN:27AAKFI9869H1ZL
A7: Contact Person | B7: Mr. Pawan Parulekar | E7: Contact Person | F7: Mr.Prathamesh Bangar
A8: Phone Number | B8: 150-6827-0160 | E8: Phone Number | F8: +91 95619 14519
A9: Email | B9: sales.yinglima@gmail.com | E9: Email ID | F9: prathamesh.darsh@gmail.com
A10: Terms of Payment: Full Payment After Documents
A11: Shiping Terms: CIF INDIA
A12: Delivery Time: Within 25 Working Days
A13: Shipment Information | L13: =(2100+1000)/O28 -> 46.629163
A14: Sr.No | B14: Description | C14: HS CODE AS PER CHINA | D14: UOM | E14: Quantity | F14: Unit Price (USD) | G14: Total Amount (USD) | H14: Unit Price(RMB) Including VAT | I14: Unit Price(RMB) Excluding VAT | J14: Including Profit 3% | K14: FOB PRICE (USD Conversion @6.7) | L14: Freight, Local charges,COC | M14: CFR Price/Unit | N14: Supplier | O14: Total CBM | P14: Total Supplier Amount
A15: 1 | B15: PFS200 Hand Sealer | C15: 8422.30.00 | D15: NOS | E15: 20 | F15: =M15 -> 5.57 | G15: =F15*E15 -> 111.4 | H15: 38.8 | I15: =H15/1.13 -> 34.336283 | J15: =(I15*1.03) -> 35.366372 | K15: =J15/6.8 -> 5.200937 | L15: =($L$13*O15)/E15 -> 0.36370747 | M15: =ROUNDUP(L15+K15,2) -> 5.57 | N15: JN | O15: 0.156 | P15: =H15*E15 -> 776
A16: 2 | B16: PSF450 Pedal Sealer | C16: 8422.30.00 | D16: NOS | E16: 2 | F16: =M16 -> 76.46 | G16: =F16*E16 -> 152.92 | H16: 532.8 | I16: =H16/1.13 -> 471.50442 | J16: =(I16*1.03) -> 485.64956 | K16: =J16/6.8 -> 71.419053 | L16: =($L$13*O16)/E16 -> 5.0359496 | M16: =ROUNDUP(L16+K16,2) -> 76.46 | N16: JN | O16: 0.216 | P16: =H16*E16 -> 1065.6
A17: 3 | B17: PSF650 Pedal Sealer | C17: 8422.30.00 | D17: NOS | E17: 2 | F17: =M17 -> 82.13 | G17: =F17*E17 -> 164.26 | H17: 588.3 | I17: =H17/1.13 -> 520.61947 | J17: =(I17*1.03) -> 536.23805 | K17: =J17/6.8 -> 78.858537 | L17: =($L$13*O17)/E17 -> 3.2640414 | M17: =ROUNDUP(L17+K17,2) -> 82.13 | N17: JN | O17: 0.14 | P17: =H17*E17 -> 1176.6
A18: 4 | B18: FR400 Band Sealer MSH | C18: 8422.40.00 | D18: NOS | E18: 30 | F18: =M18 -> 41.12 | G18: =F18*E18 -> 1233.6 | H18: 298 | I18: =H18/1.13 -> 263.71681 | J18: =(I18*1.03) -> 271.62832 | K18: =J18/6.8 -> 39.945341 | L18: =($L$13*O18)/E18 -> 1.1657291 | M18: =ROUNDUP(L18+K18,2) -> 41.12 | N18: LT | O18: 0.75 | P18: =H18*E18 -> 8940
A19: 5 | B19: DBF900L Band Sealer MSH | C19: 8422.30.00 | D19: NOS | E19: 300 | F19: =M19 -> 56.33 | G19: =F19*E19 -> 16899 | H19: 377.4 | I19: =H19/1.13 -> 333.9823 | J19: =(I19*1.03) -> 344.00177 | K19: =J19/6.8 -> 50.588496 | L19: =($L$13*O19)/E19 -> 5.735387 | M19: =ROUNDUP(L19+K19,2) -> 56.33 | N19: JN | O19: 36.9 | P19: =H19*E19 -> 113220
A20: 6 | B20: DBF900L Band Sealer SSH | C20: 8422.30.00 | D20: NOS | E20: 40 | F20: =M20 -> 72.55 | G20: =F20*E20 -> 2902 | H20: 498.39 | I20: =H20/1.13 -> 441.0531 | J20: =(I20*1.03) -> 454.28469 | K20: =J20/6.8 -> 66.806572 | L20: =($L$13*O20)/E20 -> 5.735387 | M20: =ROUNDUP(L20+K20,2) -> 72.55 | N20: JN | O20: 4.92 | P20: =H20*E20 -> 19935.6
A21: 7 | B21: LGYF2100B Continuous Induction sealer | C21: 8422.30.00 | D21: NOS | E21: 15 | F21: =M21 -> 222.71 | G21: =F21*E21 -> 3340.65 | H21: 1564 | I21: =H21/1.13 -> 1384.0708 | J21: =(I21*1.03) -> 1425.5929 | K21: =J21/6.8 -> 209.64602 | L21: =($L$13*O21)/E21 -> 13.056166 | M21: =ROUNDUP(L21+K21,2) -> 222.71 | N21: Stella | O21: 4.2 | P21: =H21*E21 -> 23460
A22: 8 | B22: DZ400 2B Vacuum machine | C22: 8422.30.00 | D22: NOS | E22: 6 | F22: =M22 -> 226.03 | G22: =F22*E22 -> 1356.18 | H22: 1554 | I22: =H22/1.13 -> 1375.2212 | J22: =(I22*1.03) -> 1416.4779 | K22: =J22/6.8 -> 208.30557 | L22: =($L$13*O22)/E22 -> 17.719082 | M22: =ROUNDUP(L22+K22,2) -> 226.03 | N22: JN | O22: 2.28 | P22: =H22*E22 -> 9324
A23: 9 | B23: DZ500 2B Vacuum machine | C23: 8422.30.00 | D23: NOS | E23: 5 | F23: =M23 -> 291.61 | G23: =F23*E23 -> 1458.05 | H23: 1998 | I23: =H23/1.13 -> 1768.1416 | J23: =(I23*1.03) -> 1821.1858 | K23: =J23/6.8 -> 267.82145 | L23: =($L$13*O23)/E23 -> 23.780873 | M23: =ROUNDUP(L23+K23,2) -> 291.61 | N23: JN | O23: 2.55 | P23: =H23*E23 -> 9990
A24: 10 | B24: FQL450 Auto L-sealer w/o Connect parts | C24: 8422.30.00 | D24: NOS | E24: 4 | F24: =M24 -> 1118.48 | G24: =F24*E24 -> 4473.92 | H24: 7370 | I24: =H24/1.13 -> 6522.1239 | J24: =(I24*1.03) -> 6717.7876 | K24: =J24/6.8 -> 987.90994 | L24: =($L$13*O24)/E24 -> 130.56166 | M24: =ROUNDUP(L24+K24,2) -> 1118.48 | N24: Yujun | O24: 11.2 | P24: =H24*E24 -> 29480
A25: 11 | B25: BSL4525 Shrink Tunnel | C25: 8422.30.00 | D25: NOS | E25: 1 | F25: =M25 -> 542.72 | G25: =F25*E25 -> 542.72 | H25: 3520 | I25: =H25/1.13 -> 3115.0442 | J25: =(I25*1.03) -> 3208.4956 | K25: =J25/6.8 -> 471.83758 | L25: =($L$13*O25)/E25 -> 70.876327 | M25: =ROUNDUP(L25+K25,2) -> 542.72 | N25: Yujun | O25: 1.52 | P25: =H25*E25 -> 3520
A26: 12 | B26: BSB3020 Shrink Tunnel Chain | C26: 8422.30.00 | D26: NOS | E26: 3 | F26: =M26 -> 137.78 | G26: =F26*E26 -> 413.34 | H26: 913 | I26: =H26/1.13 -> 807.9646 | J26: =(I26*1.03) -> 832.20354 | K26: =J26/6.8 -> 122.38287 | L26: =($L$13*O26)/E26 -> 15.387624 | M26: =ROUNDUP(L26+K26,2) -> 137.78 | N26: Yujun | O26: 0.99 | P26: =H26*E26 -> 2739
A27: 13 | B27: BSB3020 Shrink Tunnel Roller | C27: 8422.30.00 | D27: NOS | E27: 2 | F27: =M27-0.12 -> 147.98 | G27: =F27*E27 -> 295.96 | H27: 990 | I27: =H27/1.13 -> 876.10619 | J27: =(I27*1.03) -> 902.38938 | K27: =J27/6.8 -> 132.70432 | L27: =($L$13*O27)/E27 -> 15.387624 | M27: =ROUNDUP(L27+K27,2) -> 148.1 | N27: Yujun | O27: 0.66 | P27: =H27*E27 -> 1980
A28: Total Price CIF INDIA | G28: =SUM(G15:G27) -> 33344 | O28: =SUM(O15:O27) -> 66.482
A29: BANK ACCOUNT DETAILS FOR INWARD REMITTANCE USD | B29: RECEIVING BANK: INDUSTRIAL AND COMMERCIAL BANK OF CHINA,ZHEJIANG BRANCH SWIFT BIC: ICBKCNBJZJP BENEFICIARY NAME:YINGLIMA IMPORT&EXPORT (WENZHOU) CO., LTD ADDRESS:ROOM 1106 18, BUILDING 4, DEVELOPMENT BUILDING, NO.66, LINGRONG STREET, LINGKUN STREET, OUJIANGKOU INDUSTRIAL CLUSTER, WENZHOU, ZHEJIANG A/C NO:1203202009814645910
A30: Shipper's Signature and Stamp：
A31: We hereby declare that above information is true and correct.

Sheet Packing List
A1: =CI!A1 -> YINGLIMA IMPORT&EXPORT (WENZHOU) CO., LTD. Email：sales.yinglima@gmail.com Mobile：15068270160,Wechat:+91 8108294930 Address:Room 602, Sixth floor, Jinyu Business Building, Wenzhou Avenue, Nanhui Street, Lucheng District, Wenzhou City, Zhejiang Province
A2: PACKING LIST
A3: Packing List No | B3: =CI!B3 -> YL-EXP2026-54 | C3: Date | D3: =CI!G3 -> 46198
A4: Shipper's Information | C4: Recipient's Information
A5: Company Name | B5: YINGLIMA IMPORT&EXPORT (WENZHOU) CO., LTD. | C5: Company Name | D5: INHYMA SOLUTIONS LLP
A6: Address | B6: Room 602, Sixth floor, Jinyu Business Building, Wenzhou Avenue, Nanhui Street, Lucheng District, Wenzhou City, Zhejiang Province | C6: Address | D6: =CI!F6 -> Ground Floor, Godown No:2,3,4, Prerna Complex, A-9,Mankoli Road, House Number :1692/A- 9/3, VAL.Bhiwandi, Thane, Maharashtra, 421302,INDIA. GSTIN/UIN:27AAKFI9869H1ZL
A7: Contact Person | B7: Mr. Pawan Parulekar | C7: Contact Person | D7: Mr. Prathmesh Bangar
A8: Phone Number | B8: 150-6827-0160 | C8: Phone Number | D8: +91 95619 14519
A9: Email | B9: =CI!B9 -> sales.yinglima@gmail.com | C9: Email ID | D9: prathamesh.darsh@gmail.com
A10: Shiping Terms: CIF INDIA
A11: PACKING INFORMATION
A12: Sr.No | B12: Description | C12: Quantity in KGS/PCS | D12: PACKAGE | E12: UNIT OF MEASUREMENT | F12: Total in KG
F13: Net Weight | G13: Gr. Weight
A14: 1 | B14: PFS200 Hand Sealer | C14: 20 | D14: 2 | E14: NOS | F14: 61.1 | G14: 74.8
A15: 2 | B15: PSF450 Pedal Sealer | C15: 2 | D15: 2 | E15: NOS | F15: 28.9 | G15: 34
A16: 3 | B16: PSF650 Pedal Sealer | C16: 2 | D16: 2 | E16: NOS | F16: 30 | G16: 35.2
A17: 4 | B17: FR400 Band Sealer MSH | C17: 30 | D17: 30 | E17: NOS | F17: 270 | G17: 309
A18: 5 | B18: DBF900L Band Sealer MSH | C18: 300 | D18: 300 | E18: NOS | F18: 4350 | G18: 4730 | H18: 14.5 | I18: 15.6
A19: 6 | B19: DBF900L Band Sealer SSH | C19: 40 | D19: 40 | E19: NOS | F19: 580 | G19: 624 | H19: =H18*300 -> 4350 | I19: =I18*300 -> 4680
A20: 7 | B20: LGYF2100B Continuous Induction sealer | C20: 15 | D20: 15 | E20: NOS | F20: 360 | G20: 390 | H20: =H18*40 -> 580 | I20: =I18*40 -> 624
A21: 8 | B21: DZ400 2B Vacuum machine | C21: 6 | D21: 6 | E21: NOS | F21: 380 | G21: 410
A22: 9 | B22: DZ500 2B Vacuum machine | C22: 5 | D22: 5 | E22: NOS | F22: 433 | G22: 474
A23: 10 | B23: FQL450 Auto L-sealer w/o Connect parts | C23: 4 | D23: 4 | E23: NOS | F23: 1200 | G23: 1280
A24: 11 | B24: BSL4525 Shrink Tunnel | C24: 1 | D24: 1 | E24: NOS | F24: 55 | G24: 65
A25: 12 | B25: BSB3020 Shrink Tunnel Chain | C25: 3 | D25: 3 | E25: NOS | F25: 170 | G25: 190
A26: 13 | B26: BSB3020 Shrink Tunnel Roller | C26: 2 | D26: 2 | E26: NOS | F26: 125 | G26: 140
A27: Total | D27: =SUM(D14:D26) -> 412 | F27: =SUM(F14:F26) -> 8043 | G27: =SUM(G14:G26) -> 8756
A28: Shipper's Signature and Stamp：
A29: We hereby declare that above information is true and correct.
